scrape_it.py
scrape_it/__init__.py
scrape_it/correct_base.py
scrape_it/models.py
scrape_it/regex.py
scrape_it/run.py
scrape_it/scrape_it.py
scrape_it/scrape_it_experimental.py
scrape_it/scrape_policy_text.py
scrape_it-0.3.8.dist-info/METADATA
scrape_it-0.3.8.dist-info/WHEEL
scrape_it-0.3.8.dist-info/top_level.txt
scrape_it-0.3.8.dist-info/RECORD
