Metadata-Version: 2.1
Name: scrape-it
Version: 0.3.8
Summary: Systemitized tool for scraping
Home-page: https://github.com/erelin6613/Scrape_it
Author: Valentyna Fihurska
Author-email: valentineburn@gmail.com
License: Apache License 2.0
Platform: UNKNOWN
Classifier: Programming Language :: Python :: 3
Classifier: Operating System :: OS Independent
Classifier: License :: OSI Approved :: Apache Software License
Requires-Python: >=3.5
Requires-Dist: requests
Requires-Dist: tqdm
Requires-Dist: numpy
Requires-Dist: nltk
Requires-Dist: address-parser
Requires-Dist: beautifulsoup4
Requires-Dist: bs4
Requires-Dist: lxml
Requires-Dist: phonenumbers
Requires-Dist: pyap
Requires-Dist: regex
Requires-Dist: selenium
Requires-Dist: tldextract
